thonnycontrib/thonny_etboard_firmware/__init__.py
thonnycontrib/thonny_etboard_firmware/thonny_v3.py
thonnycontrib/thonny_etboard_firmware/thonny_v4.py
thonnycontrib/thonny_etboard_firmware/etboard/firmware/ReadMe.md
thonnycontrib/thonny_etboard_firmware/etboard/firmware/etboard_firmware_micropython_custom_0608_last.bin
thonnycontrib/thonny_etboard_firmware/etboard/firmware/etboard_firmware_micropython_custom_0831_last.bin
thonny_etboard_micropython_firmware-1.0.4.dist-info/LICENSE
thonny_etboard_micropython_firmware-1.0.4.dist-info/METADATA
thonny_etboard_micropython_firmware-1.0.4.dist-info/WHEEL
thonny_etboard_micropython_firmware-1.0.4.dist-info/top_level.txt
thonny_etboard_micropython_firmware-1.0.4.dist-info/RECORD
